AUTHORS.rst
CHANGELOG.rst
LICENSE
MANIFEST.in
README.rst
setup.py
django_football365.egg-info/PKG-INFO
django_football365.egg-info/SOURCES.txt
django_football365.egg-info/dependency_links.txt
django_football365.egg-info/not-zip-safe
django_football365.egg-info/requires.txt
django_football365.egg-info/top_level.txt
football365/__init__.py
football365/admin.py
football365/models.py
football365/settings.py
football365/tests.py
football365/management/__init__.py
football365/management/__init__.pyc
football365/management/commands/__init__.py
football365/management/commands/__init__.pyc
football365/management/commands/football365_fetch.py
football365/management/commands/football365_fetch.pyc
football365/migrations/0001_initial.py
football365/migrations/0002_auto__add_field_call_client_id.py
football365/migrations/0003_auto__add_field_call_url.py
football365/migrations/__init__.py