Metadata-Version: 1.1
Name: django-football365
Version: 0.2
Summary: Fetch logs, fixtures, results and live scores via the Football 365 API.
Home-page: http://github.com/praekelt/django-football365
Author: Praekelt Foundation
Author-email: dev@praekelt.com
License: BSD
Platform: UNKNOWN
Classifier: Programming Language :: Python
Classifier: License :: OSI Approved :: BSD License
Classifier: Development Status :: 4 - Beta
Classifier: Operating System :: OS Independent
Classifier: Framework :: Django
Classifier: Intended Audience :: Developers
Classifier: Topic :: Internet :: WWW/HTTP :: Dynamic Content
